AUTHORS
CHANGELOG
LICENSE
MANIFEST.in
README.rst
setup.py
deluge_webapi.egg-info/PKG-INFO
deluge_webapi.egg-info/SOURCES.txt
deluge_webapi.egg-info/dependency_links.txt
deluge_webapi.egg-info/entry_points.txt
deluge_webapi.egg-info/not-zip-safe
deluge_webapi.egg-info/top_level.txt
docs/Makefile
docs/source/conf.py
docs/source/index.rst
docs/source/quickstart.rst
docs/source/rst_guide.rst
webapi/__init__.py
webapi/common.py
webapi/core.py
webapi/gtk3ui.py
webapi/test.py
webapi/webui.py