Metadata-Version: 1.1
Name: deluge-webapi
Version: 0.4.0
Summary: Plugin for Deluge WebUI providing sane JSON API.
Home-page: https://github.com/idlesign/deluge-webapi
Author: Igor `idle sign` Starikov
Author-email: idlesign@yandex.ru
License: BSD 3-Clause License
Platform: UNKNOWN
Classifier: Development Status :: 4 - Beta
Classifier: Operating System :: OS Independent
Classifier: Programming Language :: Python
Classifier: Programming Language :: Python :: 3
Classifier: Programming Language :: Python :: 3.5
Classifier: Programming Language :: Python :: 3.6
Classifier: Programming Language :: Python :: 3.7
Classifier: License :: OSI Approved :: BSD License
Classifier: Environment :: Plugins
Classifier: Intended Audience :: End Users/Desktop
